Metadata-Version: 1.0
Name: kapoor-dist
Version: 0.1
Summary: Gaussian distributions
Home-page: UNKNOWN
Author: Siddharth Kapoor
Author-email: Siddhartgautam347@gmail.com
License: UNKNOWN
Platform: UNKNOWN
